qe_tools/__init__.py
qe_tools/_constants.py
qe_tools/_qe_version.py
qe_tools/exceptions.py
qe_tools/converters/__init__.py
qe_tools/converters/_structure.py
qe_tools/extractors/__init__.py
qe_tools/parsers/__init__.py
qe_tools/parsers/_cp_input.py
qe_tools/parsers/_input_base.py
qe_tools/parsers/_pw_input.py
qe_tools-2.3.0.dist-info/LICENSE.txt
qe_tools-2.3.0.dist-info/WHEEL
qe_tools-2.3.0.dist-info/METADATA
qe_tools-2.3.0.dist-info/RECORD
