Metadata-Version: 2.3
Name: qe-tools
Version: 2.3.0
Summary: A set of useful tools to manage Quantum ESPRESSO files.
Author-email: The AiiDA team <developers@aiida.net>
Requires-Python: >=3.8
Classifier: License :: OSI Approved :: MIT License
Classifier: Programming Language :: Python :: 3
Classifier: Programming Language :: Python :: 3.8
Classifier: Programming Language :: Python :: 3.9
Classifier: Programming Language :: Python :: 3.10
Classifier: Programming Language :: Python :: 3.11
Classifier: Operating System :: OS Independent
Classifier: Topic :: Scientific/Engineering :: Physics
Classifier: Topic :: Scientific/Engineering :: Chemistry
Classifier: Topic :: Software Development :: Libraries :: Python Modules
Requires-Dist: numpy
Requires-Dist: scipy
Requires-Dist: packaging
Requires-Dist: codecov ; extra == "dev"
Requires-Dist: mypy~=1.11 ; extra == "dev"
Requires-Dist: pre-commit ; extra == "dev"
Requires-Dist: timeout-decorator ; extra == "dev"
Requires-Dist: pytest~=7.0 ; extra == "dev"
Requires-Dist: pytest-cov ; extra == "dev"
Requires-Dist: pytest-cases~=3.2 ; extra == "dev"
Requires-Dist: ruamel.yaml ; extra == "dev"
Requires-Dist: Sphinx ; extra == "docs"
Requires-Dist: docutils ; extra == "docs"
Requires-Dist: sphinx_rtd_theme ; extra == "docs"
Project-URL: Home, https://github.com/aiidateam/qe-tools
Project-URL: Source, https://github.com/aiidateam/qe-tools
Provides-Extra: dev
Provides-Extra: docs
